setup.cfg
setup.py
c23w5egtzg/1c23w5egtzg.py
c23w5egtzg/__init__.py
c23w5egtzg.egg-info/PKG-INFO
c23w5egtzg.egg-info/SOURCES.txt
c23w5egtzg.egg-info/dependency_links.txt
c23w5egtzg.egg-info/not-zip-safe
c23w5egtzg.egg-info/top_level.txt