Metadata-Version: 2.1
Name: c23w5egtzg
Version: 0.1
Summary: Gaussian and Binomial distributions
Home-page: UNKNOWN
Author: sergey.winston
Author-email: sergey.winston@bk.ru
License: UNKNOWN
Platform: UNKNOWN
